molecule_robotframework/__init__.py
molecule_robotframework/patch_molecule_schema.py
molecule_robotframework/robotframework.py
molecule_robotframework/playbooks/verify.yml
molecule_robotframework/playbooks/verify_fetch_report.yml
molecule_robotframework/playbooks/roles/git/tasks/apt.yml
molecule_robotframework/playbooks/roles/git/tasks/dnf.yml
molecule_robotframework/playbooks/roles/git/tasks/main.yml
molecule_robotframework/playbooks/roles/git/tasks/pkg5.yml
molecule_robotframework/playbooks/roles/git/tasks/pkgng.yml
molecule_robotframework/playbooks/roles/git/tasks/unknown.yml
molecule_robotframework/playbooks/roles/git/tasks/yum.yml
molecule_robotframework/playbooks/roles/git/tasks/zypper.yml
molecule_robotframework/playbooks/roles/robotframework/.ansible-lint
molecule_robotframework/playbooks/roles/robotframework/.gitignore
molecule_robotframework/playbooks/roles/robotframework/.yamllint
molecule_robotframework/playbooks/roles/robotframework/LICENSE
molecule_robotframework/playbooks/roles/robotframework/defaults/main.yml
molecule_robotframework/playbooks/roles/robotframework/meta/main.yml
molecule_robotframework/playbooks/roles/robotframework/tasks/main.yml
molecule_robotframework/playbooks/roles/robotframework/tasks/packages/AlmaLinux-8.yml
molecule_robotframework/playbooks/roles/robotframework/tasks/packages/AlmaLinux.yml
molecule_robotframework/playbooks/roles/robotframework/tasks/packages/CentOS-6.yml
molecule_robotframework/playbooks/roles/robotframework/tasks/packages/CentOS-7.yml
molecule_robotframework/playbooks/roles/robotframework/tasks/packages/CentOS-8.yml
molecule_robotframework/playbooks/roles/robotframework/tasks/packages/Debian.yml
molecule_robotframework/playbooks/roles/robotframework/tasks/packages/Fedora.yml
molecule_robotframework/playbooks/roles/robotframework/tasks/packages/FreeBSD-11.yml
molecule_robotframework/playbooks/roles/robotframework/tasks/packages/FreeBSD.yml
molecule_robotframework-3.0.2.dist-info/LICENSE
molecule_robotframework-3.0.2.dist-info/METADATA
molecule_robotframework-3.0.2.dist-info/WHEEL
molecule_robotframework-3.0.2.dist-info/entry_points.txt
molecule_robotframework-3.0.2.dist-info/top_level.txt
molecule_robotframework-3.0.2.dist-info/RECORD
