Metadata-Version: 2.1
Name: molecule-robotframework
Version: 3.0.2
Summary: Robot Framework Molecule Plugin :: run molecule tests with Robot Framework as verifier
Home-page: https://github.com/meffie/molecule-robotframework
Author: Michael Meffie
Author-email: mmeffie@sinenomine.net
Classifier: Programming Language :: Python :: 3
Classifier: Programming Language :: Python :: 3.10
Classifier: Programming Language :: Python :: 3.11
Classifier: Programming Language :: Python :: 3.12
Classifier: License :: OSI Approved :: MIT License
Classifier: Operating System :: OS Independent
Requires-Python: >=3.10
License-File: LICENSE
Requires-Dist: molecule >=6.0.0
Requires-Dist: pyyaml >=5.1
